biobb_guild/__init__.py
biobb_guild/guild/__init__.py
biobb_guild/guild/call_guild.py
biobb_guild/guild/common.py
biobb_guild/guild/gda_disgenet.py
biobb_guild/guild/nodes.py
biobb_guild/guild/parsehippie.py
biobb_guild/guild/pre_common.py
biobb_guild/template/__init__.py
biobb_guild/template/template.py
biobb_guild/template/template_container.py
biobb_guild/test/__init__.py
biobb_guild-1.12.3.dist-info/LICENSE
biobb_guild-1.12.3.dist-info/METADATA
biobb_guild-1.12.3.dist-info/WHEEL
biobb_guild-1.12.3.dist-info/top_level.txt
biobb_guild-1.12.3.dist-info/RECORD
